{
    "$schema": "http://json-schema.org/draft-04/schema#",
    "type": "object",
    "properties": {
        "type": {
            "type": "string",
            "default": "cronjob"
        },
        "cronjob": {
            "type": "object",
            "properties": {
                "schedule": {
                    "type": "string",
                    "description": "This is the cron scheduler that you have to specify in cron format"
                },
                "suspend": {
                    "type": "boolean",
                    "description": "It will suspend all executions"
                },
                "concurreny_policy": {
                    "type": "string",
                    "description": "Specifies how to treat concurrent executions of a job that is created by this cron job.",
                    "enum": ["Allow","Forbid","Replace"]
                }
            },
            "required": [
                "schedule",
                "suspend",
                "concurreny_policy"
            ]
        },
        "job": {
            "type": "object",
            "properties": {
                "retry": {
                    "type": "integer",
                    "description": "the number of time you want to retry the job before calling it a failure"
                }
            },
            "required": [
                "retry"
            ]
        }
    },
    "required": ["job", "cronjob", "type"]
}